{
    "appid": "1716480",
    "type": "Game",
    "name": "Tied by your Red",
    "schinese_name": "",
    "isfreeapp": "0",
    "change_number": "27924129",
    "update_time": "2025-03-16 08:14:12",
    "depot": {
        "baselanguages": "tchinese",
        "1716481": {
            "config": {
                "oslist": "windows"
            },
            "manifests": {
                "public": {
                    "gid": "7523504559715186715",
                    "size": "621379687",
                    "download": "146028560"
                }
            },
            "decryptionkey": "9eebbbc4bd3ed60fe303ec8128d09ccf55cb68dbc51cb35b58206109a9e5d1d8"
        },
        "1716482": {
            "config": {
                "oslist": "macos"
            },
            "manifests": {
                "public": {
                    "gid": "441215470925809056",
                    "size": "631707379",
                    "download": "145601616"
                }
            }
        },
        "branches": {
            "public": {
                "buildid": "7796273",
                "timeupdated": "1638211065"
            }
        }
    }
}